{
  "SignIn": [],
  "search": [
    {
      "Title": "Test Item 1",
      "Description" : "Test Test"
    }
    ],
  "createUser": [
    {
      "Email": "12312312@gmail.com",
      "Password": "123123",
      "id": 1
    },
    {
      "ID": "109991914849983898782",
      "FullName": "Bo An",
      "GivenName": "Bo",
      "FamilyName": "An",
      "ImageURL": "https://lh3.googleusercontent.com/a/AATXAJw3Mv5N8vYCS67l0gMBBz2_FgF7AcEfp_7dBVW6=s96-c",
      "Email": "bo.an.563641292@gmail.com",
      "id": 2
    },
    {
      "ID": "109991914849983898782",
      "FullName": "Bo An",
      "GivenName": "Bo",
      "FamilyName": "An",
      "ImageURL": "https://lh3.googleusercontent.com/a/AATXAJw3Mv5N8vYCS67l0gMBBz2_FgF7AcEfp_7dBVW6=s96-c",
      "Email": "bo.an.563641292@gmail.com",
      "id": 3
    },
    {
      "ID": "109991914849983898782",
      "FullName": "Bo An",
      "GivenName": "Bo",
      "FamilyName": "An",
      "ImageURL": "https://lh3.googleusercontent.com/a/AATXAJw3Mv5N8vYCS67l0gMBBz2_FgF7AcEfp_7dBVW6=s96-c",
      "Email": "bo.an.563641292@gmail.com",
      "id": 4
    },
    {
      "ID": "109991914849983898782",
      "FullName": "Bo An",
      "GivenName": "Bo",
      "FamilyName": "An",
      "ImageURL": "https://lh3.googleusercontent.com/a/AATXAJw3Mv5N8vYCS67l0gMBBz2_FgF7AcEfp_7dBVW6=s96-c",
      "Email": "bo.an.563641292@gmail.com",
      "id": 5
    },
    {
      "Email": "test1@gmail.com",
      "Password": "Plmoknijb!@213",
      "id": 6
    }
  ]
}